README.rst
setup.py
lytics/__init__.py
lytics/account.py
lytics/cli.py
lytics/collect.py
lytics/config.py
lytics/csvupload.py
lytics/httpapi.py
lytics/input.py
lytics/lio.py
lytics/pretty.py
lytics/query.py
lytics/users.py
lytics.egg-info/PKG-INFO
lytics.egg-info/SOURCES.txt
lytics.egg-info/dependency_links.txt
lytics.egg-info/entry_points.txt
lytics.egg-info/not-zip-safe
lytics.egg-info/requires.txt
lytics.egg-info/top_level.txt
tests/__init__.py
tests/test1.py