Metadata-Version: 1.1
Name: lytics
Version: 0.0.12
Summary: Python CLI for Lytics.io api
Home-page: http://github.com/lytics/lyticscli
Author: Aaron Raddon
Author-email: aaron@lytics.io
License: MIT
Keywords: python
Platform: UNKNOWN
Classifier: Development Status :: 2 - Pre-Alpha
Classifier: Intended Audience :: Developers
Classifier: License :: OSI Approved :: MIT License
Classifier: Programming Language :: Python
Classifier: Topic :: Internet :: WWW/HTTP :: Dynamic Content
Classifier: Topic :: Software Development :: Libraries :: Python Modules
